mcp_docling/__init__.py
mcp_docling/__main__.py
mcp_docling/server.py
mcp_gosling-0.1.0.dist-info/METADATA
mcp_gosling-0.1.0.dist-info/WHEEL
mcp_gosling-0.1.0.dist-info/entry_points.txt
mcp_gosling-0.1.0.dist-info/licenses/LICENSE
mcp_gosling-0.1.0.dist-info/RECORD
