Metadata-Version: 2.4
Name: mcp-gosling
Version: 0.1.0
Summary: MCP Gosling - Advanced document processing server for Goose AI using IBM's Docling library
Project-URL: Homepage, https://github.com/masanderso/goose-docling
Project-URL: Repository, https://github.com/masanderso/goose-docling
Project-URL: Issues, https://github.com/masanderso/goose-docling/issues
Author-email: Michael Anderson <masanderso@users.noreply.github.com>
License-Expression: MIT
License-File: LICENSE
Keywords: ai,docling,document-processing,goose,mcp,model-context-protocol,pdf,server,text-extraction
Classifier: Development Status :: 4 - Beta
Classifier: Intended Audience :: Developers
Classifier: License :: OSI Approved :: MIT License
Classifier: Operating System :: OS Independent
Classifier: Programming Language :: Python :: 3
Classifier: Programming Language :: Python :: 3.9
Classifier: Programming Language :: Python :: 3.10
Classifier: Programming Language :: Python :: 3.11
Classifier: Programming Language :: Python :: 3.12
Requires-Python: >=3.9
Requires-Dist: certifi>=2023.7.22
Requires-Dist: docling>=2.0.0
Requires-Dist: mcp[cli]>=1.2.0
Requires-Dist: pypdf2>=3.0.0
Provides-Extra: dev
Requires-Dist: black>=23.0.0; extra == 'dev'
Requires-Dist: isort>=5.12.0; extra == 'dev'
Requires-Dist: mypy>=1.0.0; extra == 'dev'
Requires-Dist: pytest-asyncio>=0.21.0; extra == 'dev'
Requires-Dist: pytest>=7.0.0; extra == 'dev'
Provides-Extra: uvx
